{
  "sections": [
    {
      "id": "about",
      "categoryId": "home",
      "jsonPath": "/sections/cover.json",
      "faIcon": "fa-solid fa-address-card",
      "type": "centered",
      "locales": {
        "en": {
          "title": "From strengh coach to Unix server !",
          "title_short": "Welcome!",
          "description": null,
          "nav_label": "About"
        },
        "fr": {
          "title": "De la prépa physique aux serveurs Linux !",
          "title_short": "Bienvenue !",
          "description": null,
          "nav_label": "À propos"
        }
      }
    },
    {
      "id": "education",
      "categoryId": "background",
      "jsonPath": "/sections/education.json",
      "faIcon": "fa-solid fa-graduation-cap",
      "type": "column",
      "locales": {
        "en": {
          "title": "*Education* Background",
          "title_short": null,
          "description": "A glimpse into my academic trajectory and accomplishments.",
          "nav_label": "Education"
        },
        "fr": {
          "title": "Parcours *Éducatif*",
          "title_short": null,
          "description": "Un aperçu de mon parcours académique et de mes réalisations.",
          "nav_label": "Éducation"
        }
      }
    },
    {
      "id": "skills",
      "categoryId": "showcase",
      "jsonPath": "/sections/skills.json",
      "faIcon": "fa-solid fa-tools",
      "type": "column",
      "locales": {
        "en": {
          "title": "*Skill* Set",
          "title_short": null,
          "description": "Exploring the diverse range of skills I've acquired and developed:",
          "nav_label": "Skills"
        },
        "fr": {
          "title": "Ensemble de *Compétences*",
          "title_short": null,
          "description": "Exploration de la gamme variée de compétences que j'ai acquises et développées:",
          "nav_label": "Compétences"
        }
      }
    },
    {
      "id": "experience",
      "categoryId": "background",
      "jsonPath": "/sections/experience.json",
      "faIcon": "fa-solid fa-briefcase",
      "type": "column",
      "locales": {
        "en": {
          "title": "*Professional* Experience",
          "title_short": null,
          "description": "A look into my work experience and career journey.",
          "nav_label": "Experience"
        },
        "fr": {
          "title": "Expérience *Professionnelle*",
          "title_short": null,
          "description": "Un aperçu de mon expérience professionnelle et de mon parcours de carrière.",
          "nav_label": "Expérience"
        }
      }
    },
    {
      "id": "portfolio",
      "categoryId": "showcase",
      "jsonPath": "/sections/portfolio.json",
      "faIcon": "fa-solid fa-folder-open",
      "type": "column",
      "locales": {
        "en": {
          "title": "My *Portfolio*",
          "title_short": null,
          "description": "Explore a selection of my recent projects and creative works.",
          "nav_label": "Portfolio"
        },
        "fr": {
          "title": "Mon *Portfolio*",
          "title_short": null,
          "description": "Découvrez une sélection de mes projets récents et œuvres créatives.",
          "nav_label": "Portfolio"
        }
      }
    },
    {
      "id": "achievements",
      "categoryId": "showcase",
      "jsonPath": "/sections/achievements.json",
      "faIcon": "fa-solid fa-award",
      "type": "row",
      "locales": {
        "en": {
          "title": "Career *Achievements*",
          "title_short": null,
          "description": "No IT trophies to show yet — but here are a few achievements as strengh coach !",
          "nav_label": "Achievements"
        },
        "fr": {
          "title": "Réalisations *Professionnelles*",
          "title_short": null,
          "description": "Pas encore de trophées en informatique — mais voici quelques réalisations en tant que préparateur physique !",
          "nav_label": "Réalisations"
        }
      }
    },
    {
      "id": "hobbies",
      "categoryId": "more",
      "jsonPath": "/sections/hobbies.json",
      "faIcon": "fa-solid fa-heart",
      "type": "column",
      "locales": {
        "en": {
          "title": "*Hobbies* & Interests",
          "title_short": null,
          "description": "This is pretty much how I spend my free time:",
          "nav_label": "Hobbies"
        },
        "es": {
          "title": "*Pasatiempos* e Intereses",
          "title_short": null,
          "description": "Así es más o menos cómo paso mi tiempo libre:",
          "nav_label": "Aficiones"
        },
        "fr": {
          "title": "*Loisirs* et Intérêts",
          "title_short": null,
          "description": "C'est à peu près ainsi que je passe mon temps libre:",
          "nav_label": "Loisirs"
        },
        "zh": {
          "title": "*爱好*与兴趣",
          "title_short": null,
          "description": "这基本上是我空闲时间的安排：",
          "nav_label": "兴趣爱好"
        }
      }
    },
    {
      "id": "contact",
      "categoryId": "more",
      "jsonPath": "/sections/contact.json",
      "faIcon": "fa-solid fa-pen-to-square",
      "type": "column",
      "locales": {
        "en": {
          "title": "*Contact* Me",
          "title_short": null,
          "description": "Please don't hesitate to get in touch with me !",
          "nav_label": "Contact"
        },
        "fr": {
          "title": "*Contactez*-moi",
          "title_short": null,
          "description": "N'hésitez pas à me contacter !",
          "nav_label": "Contact"
        }
      }
    }
  ]
}